script_manager/__init__.py
script_manager/command.py
script_manager/utils.py
script_manager/compat/__init__.py
script_manager/compat/typing.py
script_manager-0.3.0.dist-info/LICENSE
script_manager-0.3.0.dist-info/METADATA
script_manager-0.3.0.dist-info/WHEEL
script_manager-0.3.0.dist-info/top_level.txt
script_manager-0.3.0.dist-info/RECORD
