Metadata-Version: 2.1
Name: script-manager
Version: 0.3.0
Summary: An elegant command-line interface. Usage like Flask-Script but more powerful and universal.
Home-page: https://github.com/yetone/script-manager
Author: yetone
Author-email: yetoneful@gmail.com
License: MIT License
Keywords: command-line interface,flask_script,argparse,script
Platform: any
Classifier: Intended Audience :: Developers
Classifier: Topic :: Documentation
Classifier: License :: OSI Approved :: MIT License
Classifier: Programming Language :: Python
Classifier: Programming Language :: Python :: 2.7
Classifier: Programming Language :: Python :: 3
Classifier: Programming Language :: Python :: 3.2
Classifier: Programming Language :: Python :: 3.3
Classifier: Programming Language :: Python :: 3.4
Classifier: Programming Language :: Python :: 3.5
Classifier: Programming Language :: Python :: 3.6
Classifier: Programming Language :: Python :: 3.7
Classifier: Topic :: Software Development
Classifier: Topic :: Utilities
